viledayacloud/__init__.py
viledayacloud/common.py
viledayacloud-1.0.22.dist-info/METADATA
viledayacloud-1.0.22.dist-info/WHEEL
viledayacloud-1.0.22.dist-info/top_level.txt
viledayacloud-1.0.22.dist-info/RECORD
